akindofmagic-0.4.18.dist-info/DESCRIPTION.rst
akindofmagic-0.4.18.dist-info/METADATA
akindofmagic-0.4.18.dist-info/RECORD
akindofmagic-0.4.18.dist-info/WHEEL
akindofmagic-0.4.18.dist-info/metadata.json
akindofmagic-0.4.18.dist-info/top_level.txt
magic/__init__.py
magic/libmagic.py
magic/utility.py
magic/test/__init__.py
magic/test/test_magic.py
magic/test/data/test.zip
magic/win32/libgcc_s_dw2-1.dll
magic/win32/libiconv-2.dll
magic/win32/libintl-8.dll
magic/win32/libsystre-0.dll
magic/win32/libtre-5.dll
magic/win32/libwinpthread-1.dll
magic/win32/magic.mgc
magic/win32/magic1.dll
magic/win32/regex2.dll
magic/win32/zlib1.dll
magic/win64/libgnurx-0.dll
magic/win64/libiconv-2.dll
magic/win64/libintl-8.dll
magic/win64/libsystre-0.dll
magic/win64/libtre-5.dll
magic/win64/magic.mgc
magic/win64/magic1.dll
