Metadata-Version: 2.0
Name: akindofmagic
Version: 0.4.18
Summary: File type identification using libmagic
Home-page: http://github.com/tritium21/akindofmagic
Author: Alex Walters
Author-email: tritium@sdamon.com
License: MIT
Keywords: mime magic file
Platform: UNKNOWN
Classifier: Intended Audience :: Developers
Classifier: License :: OSI Approved :: MIT License
Classifier: Programming Language :: Python
Classifier: Programming Language :: Python :: 2
Classifier: Programming Language :: Python :: 3
